volsense_core/__init__.py
volsense_core/forecaster_core.py
volsense_core/__pycache__/__init__.cpython-311.pyc
volsense_core/__pycache__/forecaster_core.cpython-311.pyc
volsense_core/cli/train_model.py
volsense_core/cli/__pycache__/train_model.cpython-311.pyc
volsense_core/data/__init__.py
volsense_core/data/data_utils.py
volsense_core/data/feature_engineering.py
volsense_core/data/fetch.py
volsense_core/data/__pycache__/__init__.cpython-311.pyc
volsense_core/data/__pycache__/data_utils.cpython-311.pyc
volsense_core/data/__pycache__/feature_engineering.cpython-311.pyc
volsense_core/data/__pycache__/fetch.cpython-311.pyc
volsense_core/data/__pycache__/fetch_yf.cpython-311.pyc
volsense_core/data/__pycache__/multi_fetch.cpython-311.pyc
volsense_core/evaluation/evaluation.py
volsense_core/evaluation/metrics.py
volsense_core/evaluation/__pycache__/evaluation.cpython-311.pyc
volsense_core/evaluation/__pycache__/feature_selection.cpython-311.pyc
volsense_core/evaluation/__pycache__/metrics.cpython-311.pyc
volsense_core/models/__init__.py
volsense_core/models/garch_methods.py
volsense_core/models/global_vol_forecaster.py
volsense_core/models/lstm_forecaster.py
volsense_core/models/__pycache__/__init__.cpython-311.pyc
volsense_core/models/__pycache__/garch_methods.cpython-311.pyc
volsense_core/models/__pycache__/global_vol_forecaster.cpython-311.pyc
volsense_core/models/__pycache__/lstm_forecaster.cpython-311.pyc
volsense_core/models/__pycache__/volnetx.cpython-311.pyc
volsense_core/utils/checkpoint_utils.py
volsense_core/utils/scalers.py
volsense_core/utils/__pycache__/checkpoint_utils.cpython-311.pyc
volsense_core/utils/__pycache__/scalers.cpython-311.pyc
volsense_inference/__init__.py
volsense_inference/analytics.py
volsense_inference/dashboard.py
volsense_inference/forecast_engine.py
volsense_inference/model_loader.py
volsense_inference/predictor.py
volsense_inference/sector_mapping.py
volsense_inference/signal_engine.py
volsense-1.0.2.dist-info/METADATA
volsense-1.0.2.dist-info/WHEEL
volsense-1.0.2.dist-info/entry_points.txt
volsense-1.0.2.dist-info/top_level.txt
volsense-1.0.2.dist-info/RECORD
