Metadata-Version: 2.4
Name: volsense
Version: 1.0.2
Summary: Explainable volatility forecasting and signal intelligence framework
Author-email: Rahul Karthik <rahul.m.karthik@gmail.com>
License: MIT
Project-URL: Homepage, https://github.com/rahulmkarthik/VolSense
Project-URL: Source, https://github.com/rahulmkarthik/VolSense
Project-URL: Issues, https://github.com/rahulmkarthik/VolSense/issues
Keywords: volatility,time-series,deep-learning,explainable-ai,quantitative-finance,trading-signals
Classifier: Programming Language :: Python :: 3
Classifier: Programming Language :: Python :: 3.11
Classifier: License :: OSI Approved :: MIT License
Classifier: Operating System :: OS Independent
Classifier: Intended Audience :: Science/Research
Classifier: Topic :: Scientific/Engineering :: Artificial Intelligence
Classifier: Topic :: Office/Business :: Financial
Requires-Python: >=3.10
Requires-Dist: numpy>=1.24
Requires-Dist: pandas>=2.0
Requires-Dist: scipy>=1.11
Requires-Dist: arch>=6.3.0
Requires-Dist: statsmodels>=0.14
Requires-Dist: torch>=2.2
Requires-Dist: torchvision>=0.17
Requires-Dist: torchaudio>=2.2
Requires-Dist: matplotlib>=3.8
Requires-Dist: seaborn>=0.13
Requires-Dist: plotly>=5.18
Requires-Dist: yfinance>=0.2.40
Requires-Dist: requests>=2.31
Requires-Dist: scikit-learn>=1.3
Requires-Dist: tqdm>=4.66
Requires-Dist: streamlit>=1.33
Provides-Extra: notebook
Requires-Dist: jupyterlab>=4.0; extra == "notebook"
Requires-Dist: notebook>=7; extra == "notebook"
Requires-Dist: ipykernel; extra == "notebook"
Requires-Dist: ipywidgets; extra == "notebook"
Provides-Extra: explain
Requires-Dist: numba>=0.57; extra == "explain"
Requires-Dist: cloudpickle>=2.2; extra == "explain"
Provides-Extra: dev
Requires-Dist: pytest>=7.4; extra == "dev"
Requires-Dist: pytest-cov; extra == "dev"
Requires-Dist: black; extra == "dev"
Requires-Dist: isort; extra == "dev"
Requires-Dist: mypy; extra == "dev"
